{
  "info": {
    "description": "A service whose API version is pinned by an explicit service-level engine annotation.\n Regardless of what options.version is set to, the annotation version always wins.",
    "title": "PinnedVersionService",
    "version": "pinned-1.0.0"
  },
  "openapi": "3.1.0",
  "paths": {
    "/DoIt": {
      "get": {
        "description": "Gets a widget by its identifier.",
        "operationId": "PinnedVersionService_DoIt",
        "responses": {
          "200": {
            "description": "OK"
          }
        },
        "summary": "Gets a widget by its identifier."
      }
    }
  }
}
